LICENSE
README.md
setup.py
Dictionary/Dictionary.py
Dictionary/ExceptionalWord.py
Dictionary/Pos.py
Dictionary/TxtDictionary.py
Dictionary/TxtWord.py
Dictionary/VectorizedDictionary.py
Dictionary/VectorizedWord.py
Dictionary/Word.py
Dictionary/__init__.py
Dictionary/Trie/Trie.py
Dictionary/Trie/TrieNode.py
Dictionary/Trie/__init__.py
Dictionary/data/__init__.py
Dictionary/data/turkish_dictionary.txt
Dictionary/data/turkish_misspellings.txt
Dictionary/data/turkish_morphological_lexicon.txt
Language/EnglishLanguage.py
Language/Language.py
Language/TurkishLanguage.py
Language/__init__.py
NlpToolkit_Dictionary.egg-info/PKG-INFO
NlpToolkit_Dictionary.egg-info/SOURCES.txt
NlpToolkit_Dictionary.egg-info/dependency_links.txt
NlpToolkit_Dictionary.egg-info/requires.txt
NlpToolkit_Dictionary.egg-info/top_level.txt
Syllibification/Syllable.py
Syllibification/SyllableList.py
Syllibification/__init__.py