Metadata-Version: 2.1
Name: NlpToolkit-Dictionary
Version: 1.0.29
Summary: Simple Dictionary Processing
Home-page: https://github.com/StarlangSoftware/Dictionary-Py
Author: olcaytaner
Author-email: olcay.yildiz@ozyegin.edu.tr
License: UNKNOWN
Platform: UNKNOWN
License-File: LICENSE
